{
  "languageserver": {
    "rust": {
      "command": "rust-analyzer",
      "filetypes": ["rust"],
      "rootPatterns": ["Cargo.toml"]
    },
    "clangd": {
      "command": "clangd",
      "rootPatterns": [ "compile_commands.json" ],
      "filetypes": ["c", "cc", "cpp", "c++", "objc", "objcpp"]
    }
  },
  "cSpell.userWords": [
    "Alessandro",
    "Pezzato",
    "alepez"
  ],
  "cSpell.enabled": false,
  "codeLens.enable": true,
  "diagnostic.virtualText": true,
  "git.addGBlameToBufferVar": true,
  "git.addGBlameToVirtualText": true
}
